{
  "table": {
    "type": "table",
    "ignore": "boolean",
    "selectable": "boolean",
    "payload": {
      "error": "string",
      "offset": "int",
      "limit": "int",
      "pageCount": "int",
      "columns": [
        {
          "id": "date",
          "title": "string",
          "type": "primitiveType | libraryComponent"
        },
        {
          "id": "order",
          "title": "string",
          "type": "primitiveType | libraryComponent"
        }
      ]
    }
  }
}

// передача в заголовках лимит оффсет
"id": "order",
"title": "string",
"type": "primitiveType"